gitconsensus/__init__.py
gitconsensus/config.py
gitconsensus/gitconsensus.py
gitconsensus/repository.py
gitconsensus-0.8.0.dist-info/LICENSE.txt
gitconsensus-0.8.0.dist-info/METADATA
gitconsensus-0.8.0.dist-info/WHEEL
gitconsensus-0.8.0.dist-info/entry_points.txt
gitconsensus-0.8.0.dist-info/top_level.txt
gitconsensus-0.8.0.dist-info/RECORD
