Metadata-Version: 2.1
Name: gitconsensus
Version: 0.8.0
Summary: Automate Github Pull Requests using Reactions
Home-page: https://github.com/gitconsensus/gitconsensuscli
Author: Robert Hafner
Author-email: tedivm@tedivm.com
License: UNKNOWN
Download-URL: https://github.com/gitconsensus/gitconsensuscli/archive/v0.8.0.tar.gz
Keywords: automation github consensus git
Platform: UNKNOWN
Classifier: Development Status :: 4 - Beta
Classifier: License :: OSI Approved :: MIT License
Classifier: Intended Audience :: Developers
Classifier: Intended Audience :: System Administrators
Classifier: Topic :: Software Development :: Version Control
Classifier: Programming Language :: Python :: 3
Classifier: Environment :: Console
Requires-Python: >=3
Requires-Dist: click (<8.0,>=6.0)
Requires-Dist: github3.py (<2,>=1)
Requires-Dist: PyYAML (<6,>=3.12)
Requires-Dist: requests (<3,>=2.18.0)
Requires-Dist: semantic-version (<3,>=2.6.0)
Provides-Extra: dev
Requires-Dist: twine ; extra == 'dev'
Requires-Dist: wheel ; extra == 'dev'
